zen_publish/__init__.py
zen_publish/core/__init__.py
zen_publish/core/publish.py
zen_publish/core/worker.py
zen_publish/support/__init__.py
zen_publish/support/config_template.py
zen_publish/support/cred.py
zen_publish-0.0.23.dist-info/LICENSE
zen_publish-0.0.23.dist-info/METADATA
zen_publish-0.0.23.dist-info/WHEEL
zen_publish-0.0.23.dist-info/dependency_links.txt
zen_publish-0.0.23.dist-info/entry_points.txt
zen_publish-0.0.23.dist-info/top_level.txt
zen_publish-0.0.23.dist-info/RECORD
