Metadata-Version: 2.1
Name: zen-publish
Version: 0.0.23
Summary: Package for Zen Reports
Home-page: UNKNOWN
Author: Dr. P. B. Patel
Author-email: customer.support@zenreportz.atlassian.net
License: Apache License
Platform: UNKNOWN
Classifier: Programming Language :: Python :: 3
Classifier: Operating System :: OS Independent
Requires-Python: >=3
License-File: LICENSE
Requires-Dist: click
Requires-Dist: oyaml
Requires-Dist: requests
